fairdetect_groupb/__init__.py
fairdetect_groupb-0.47.dist-info/METADATA
fairdetect_groupb-0.47.dist-info/WHEEL
fairdetect_groupb-0.47.dist-info/desktop.ini
fairdetect_groupb-0.47.dist-info/top_level.txt
fairdetect_groupb-0.47.dist-info/RECORD
