Metadata-Version: 2.1
Name: fairdetect-groupb
Version: 0.47
Summary: Library to identify bias in pre-trained models!
Home-page: https://github.com/dianisley/fairdetect_b
Author: GMBD_Group_B
Author-email: Carlos.BlazquezP@student.ie.edu
License: MIT
Platform: UNKNOWN
Requires-Dist: dalex (>=1.4.1)
